ddwrtdb
