Metadata-Version: 1.1
Name: ddwrtdb
Version: 0.1.1
Summary: Simple CLI to search on DD-WRT router database and retrieve router information.
Home-page: https://github.com/turicas/ddwrtdb/
Author: Álvaro Justen
Author-email: alvarojusten@gmail.com
License: UNKNOWN
Keywords: dd-wrt,router,database,tabular,table
Platform: UNKNOWN
Classifier: Development Status :: 3 - Alpha
Classifier: Intended Audience :: Developers
Classifier: Intended Audience :: Science/Research
Classifier: License :: OSI Approved :: GNU General Public License v3 or later (GPLv3+)
Classifier: Natural Language :: English
Classifier: Operating System :: OS Independent
Classifier: Programming Language :: Python :: 2.7
